[
  {
    "url": "http://picsum.photos/300/300",
    "likeCount": 123,
    "commentCount": 321
  },
  {
    "url": "http://picsum.photos/400/300",
    "likeCount": 23,
    "commentCount": 21
  },
  {
    "url": "http://picsum.photos/300/400",
    "likeCount": 1,
    "commentCount": 23
  },
  {
    "url": "http://picsum.photos/1000/1000",
    "likeCount": 233,
    "commentCount": 1
  },
  {
    "url": "http://picsum.photos/300/340",
    "likeCount": 12364,
    "commentCount": 999
  },
  {
    "url": "http://picsum.photos/300/350",
    "likeCount": 445,
    "commentCount": 232
  },
  {
    "url": "http://picsum.photos/300/360",
    "likeCount": 2348,
    "commentCount": 2321
  },
  {
    "url": "http://picsum.photos/300/370",
    "likeCount": 232,
    "commentCount": 56
  },
  {
    "url": "http://picsum.photos/300/380",
    "likeCount": 7876,
    "commentCount": 87
  },
  {
    "url": "http://picsum.photos/300/390",
    "likeCount": 456,
    "commentCount": 123
  },
  {
    "url": "http://picsum.photos/2000/2000",
    "likeCount": 768,
    "commentCount": 575
  },
  {
    "url": "http://picsum.photos/320/300",
    "likeCount": 336,
    "commentCount": 543
  },
  {
    "url": "http://picsum.photos/330/300",
    "likeCount": 32,
    "commentCount": 69
  },
  {
    "url": "http://picsum.photos/340/300",
    "likeCount": 94664784,
    "commentCount": 123456744
  },
  {
    "url": "http://picsum.photos/350/300",
    "likeCount": 123,
    "commentCount": 65
  },
  {
    "url": "http://picsum.photos/360/300",
    "likeCount": 6756,
    "commentCount": 45
  },
  {
    "url": "http://picsum.photos/370/300",
    "likeCount": 23234,
    "commentCount": 434
  }
]
